MANIFEST.in
README.md
setup.py
django_mapbox_location_field.egg-info/PKG-INFO
django_mapbox_location_field.egg-info/SOURCES.txt
django_mapbox_location_field.egg-info/dependency_links.txt
django_mapbox_location_field.egg-info/requires.txt
django_mapbox_location_field.egg-info/top_level.txt
mapbox_location_field/__init__.py
mapbox_location_field/admin.py
mapbox_location_field/apps.py
mapbox_location_field/forms.py
mapbox_location_field/models.py
mapbox_location_field/widgets.py
mapbox_location_field/spatial/admin.py
mapbox_location_field/spatial/forms.py
mapbox_location_field/spatial/models.py
mapbox_location_field/static/mapbox_location_field/css/address_input.css
mapbox_location_field/static/mapbox_location_field/css/map_input.css
mapbox_location_field/static/mapbox_location_field/js/address_input.js
mapbox_location_field/static/mapbox_location_field/js/map_input.js
mapbox_location_field/templates/default_django/attrs.html
mapbox_location_field/templates/default_django/input.html
mapbox_location_field/templates/mapbox_location_field/address_input.html
mapbox_location_field/templates/mapbox_location_field/admin_change.html
mapbox_location_field/templates/mapbox_location_field/map_input.html
mapbox_location_field/templatetags/__init__.py
mapbox_location_field/templatetags/mapbox_location_field_tags.py
mapbox_location_field/templatetags/transform_map_attrs_to_js.py