Metadata-Version: 2.1
Name: django-mapbox-location-field
Version: 1.7.4
Summary: location field with MapInput widget for picking some location
Home-page: https://github.com/Simon-the-Shark/django-mapbox-location-field
Author: Szymon Kowaliński
Author-email: contact@kowalinski.dev
License: MIT License
Download-URL: https://github.com/Simon-the-Shark/django-mapbox-location-field/archive/v1.7.3.tar.gz
Keywords: DJANGO,WIDGETS,LOCATION,GEOCODING,MAP,FIELDS,FORMS
Platform: UNKNOWN
Classifier: Development Status :: 4 - Beta
Classifier: Environment :: Web Environment
Classifier: Framework :: Django
Classifier: Framework :: Django :: 1.11
Classifier: Framework :: Django :: 2.0
Classifier: Framework :: Django :: 2.1
Classifier: Framework :: Django :: 2.2
Classifier: Intended Audience :: Developers
Classifier: License :: OSI Approved :: MIT License
Classifier: Operating System :: OS Independent
Classifier: Programming Language :: Python
Classifier: Programming Language :: Python :: 3
Classifier: Programming Language :: Python :: 3.5
Classifier: Programming Language :: Python :: 3.6
Classifier: Programming Language :: Python :: 3.7
Classifier: Topic :: Software Development
Classifier: Topic :: Software Development :: Libraries :: Application Frameworks
Classifier: Topic :: Internet :: WWW/HTTP
Classifier: Topic :: Internet :: WWW/HTTP :: Dynamic Content
